commonvoice_utils-0.2.30.data/scripts/covo
cvutils/__init__.py
cvutils/alphabet.py
cvutils/att.py
cvutils/corpora.py
cvutils/gutenberg.py
cvutils/opus.weights
cvutils/phonemiser.py
cvutils/segmenter.py
cvutils/tagger.py
cvutils/tokeniser.py
cvutils/transliterator.py
cvutils/validator.py
cvutils/wikipedia.py
cvutils/data/ab/alphabet.txt
cvutils/data/ab/phon.tsv
cvutils/data/ab/validate.tsv
cvutils/data/ab/vocab.tsv
cvutils/data/am/alphabet.txt
cvutils/data/am/phon.tsv
cvutils/data/am/validate.tsv
cvutils/data/ar/alphabet.txt
cvutils/data/ar/validate.tsv
cvutils/data/ar/vocab.tsv
cvutils/data/as/alphabet.txt
cvutils/data/as/phon.tsv
cvutils/data/as/validate.tsv
cvutils/data/ast/alphabet.txt
cvutils/data/ast/validate.tsv
cvutils/data/az/alphabet.txt
cvutils/data/az/phon.tsv
cvutils/data/az/validate.tsv
cvutils/data/azz/alphabet.txt
cvutils/data/azz/phon.tsv
cvutils/data/azz/validate.tsv
cvutils/data/ba/alphabet.txt
cvutils/data/ba/phon.tsv
cvutils/data/ba/validate.tsv
cvutils/data/ba/vocab.tsv
cvutils/data/bas/alphabet.txt
cvutils/data/bas/phon.tsv
cvutils/data/bas/validate.tsv
cvutils/data/bas/wikipedia.txt
cvutils/data/be/alphabet.txt
cvutils/data/be/phon.tsv
cvutils/data/be/validate.tsv
cvutils/data/bg/alphabet.txt
cvutils/data/bg/phon.tsv
cvutils/data/bg/validate.tsv
cvutils/data/bn/abbr.tsv
cvutils/data/bn/alphabet.txt
cvutils/data/bn/punct.tsv
cvutils/data/bn/validate.tsv
cvutils/data/br/abbr.tsv
cvutils/data/br/alphabet.txt
cvutils/data/br/phon.tsv
cvutils/data/br/punct.tsv
cvutils/data/br/validate.tsv
cvutils/data/br/vocab.tsv
cvutils/data/ca/alphabet.txt
cvutils/data/ca/validate.tsv
cvutils/data/ca/vocab.tsv
cvutils/data/ckb/alphabet.txt
cvutils/data/ckb/phon.tsv
cvutils/data/ckb/validate.tsv
cvutils/data/ckt/alphabet.txt
cvutils/data/ckt/phon.tsv
cvutils/data/ckt/validate.tsv
cvutils/data/cnh/alphabet.txt
cvutils/data/cnh/validate.tsv
cvutils/data/cs/alphabet.txt
cvutils/data/cs/phon.tsv
cvutils/data/cs/validate.tsv
cvutils/data/cs/vocab.tsv
commonvoice_utils-0.2.30.dist-info/COPYING
commonvoice_utils-0.2.30.dist-info/METADATA
commonvoice_utils-0.2.30.dist-info/WHEEL
commonvoice_utils-0.2.30.dist-info/top_level.txt
commonvoice_utils-0.2.30.dist-info/RECORD
