Metadata-Version: 2.1
Name: commonvoice-utils
Version: 0.2.30
Summary: Linguistic processing for languages in Common Voice
Home-page: https://github.com/ftyers/commonvoice-utils
Author: Francis M. Tyers
Author-email: ftyers@prompsit.com
License: AGPL
Platform: UNKNOWN
Classifier: License :: OSI Approved :: GNU Affero General Public License v3 or later (AGPLv3+)
Classifier: Programming Language :: Python :: 3
Classifier: Programming Language :: Python :: 3.7
